sgp/__init__.py
sgp/kernel.py
sgp/variational.py
sgp-0.2.1.dist-info/METADATA
sgp-0.2.1.dist-info/RECORD
sgp-0.2.1.dist-info/WHEEL
sgp-0.2.1.dist-info/top_level.txt
