Metadata-Version: 2.1
Name: sgp
Version: 0.2.1
Summary: Sparse gaussian process regression
Home-page: https://github.com/marnikitta/sgp
Author: Nikita Marshalkin
Author-email: marnikitta@gmail.com
License: UNKNOWN
Platform: UNKNOWN
Classifier: Programming Language :: Python :: 3
Classifier: License :: OSI Approved :: MIT License
Classifier: Operating System :: OS Independent
